<?xml version="1.0" ?>
<?xml-stylesheet type='text/xsl' href='interface.xsl'?>
<interface uri="http://mojo.informatik.uni-erlangen.de/interfaces/2011/firefox.xml" xmlns="http://zero-install.sourceforge.net/2004/injector/interface">
  <name>Firefox</name>
  <summary>Mozilla Firefox Web browser</summary>
  <description>
Mozilla Firefox is an open-source web browser, designed for standards
compliance, performance and portability.</description>
  <homepage>http://www.mozilla.com/firefox/</homepage>
  <category>Network</category>
  <icon href="http://people.mozilla.com/~faaborg/files/shiretoko/firefoxIcon/firefox-256.png" type="image/png"/>
  <group license="OSI Approved :: Mozilla Public License (MPL)">
    <group released="2011-09-29" stability="stable" version="7.0.1">
      <implementation arch="Linux-x86_64" id="sha1new=289602c79163f605a5e74cc5a718d1d7158522c2" main="firefox" released="2011-09-30" version="7.0.1">
        <archive extract="firefox" href="http://3347-mozilla.voxcdn.com/pub/mozilla.org/firefox/releases/7.0.1/linux-x86_64/en-US/firefox-7.0.1.tar.bz2" size="16905662" type="application/x-bzip-compressed-tar"/>
      </implementation>
      <implementation arch="Linux-i686" id="sha1new=6afd7783f7f2e60a03c8ff06db9aab60ba0fdae2" main="firefox" released="2011-09-30" version="7.0.1">
        <archive extract="firefox" href="http://download.mozilla.org/?product=firefox-7.0.1&amp;os=linux&amp;lang=en-US" size="15252909" type="application/x-bzip-compressed-tar"/>
      </implementation>
    </group>
    <requires interface="http://mojo.informatik.uni-erlangen.de/interfaces/2011/gtk2.xml"/>
  </group>
  <package-implementation distributions="Debian RPM" main="/usr/bin/firefox" package="firefox"/>
  <package-implementation distributions="RPM" main="/usr/bin/firefox" package="MozillaFirefox"/>
  <package-implementation distributions="Gentoo" main="/usr/bin/firefox" package="www-client/firefox"/>
  <package-implementation distributions="Debian" main="/usr/bin/iceweasel" package="iceweasel"/>
</interface>
<!-- Base64 Signature
iQEcBAABAgAGBQJOhdgXAAoJEFX/wTZE6YDhq7sIAJRb+O9/0gw2p+pDXlP0OyejEHrhY+nQfIPj
k5A4EaKQEWQGqcDQ/nGlkg+1KJLGEA5eC69HS8LN8wkQ2s7hd9IZrqeLThEIKUgwzTeXV8IwlMuL
S6pORoCPHNFmDe7ujGrHVRRUYrKZcBt6FiolM2LUoeyP4o4Q3KYqKXKIUqavAY3Qb7xuA7YsBtRm
CcQvjxH8iXa88Q6ss42x4Lr5pypofA5RYNR4xXf656J/p9Kr0/UPCt6exXjhp1Y/1S3SXlmHt1EU
bJx66a/ev1rkxB/Y7AHQzPtrS4zMpxZD4OPi1dVVK1QZRf7NFCBHfl432hxUnDa2fK/iqLY4dr/i
N5k=

-->
